fstd2nc_deps-0.20200304.6.data/purelib/fstd2nc_deps/Fstdc.py
fstd2nc_deps-0.20200304.6.data/purelib/fstd2nc_deps/__init__.py
fstd2nc_deps-0.20200304.6.data/purelib/fstd2nc_deps/rpn_helpers.py
fstd2nc_deps-0.20200304.6.data/purelib/fstd2nc_deps/rpnstd.py
fstd2nc_deps-0.20200304.6.data/purelib/fstd2nc_deps/rpnpy/__init__.py
fstd2nc_deps-0.20200304.6.data/purelib/fstd2nc_deps/rpnpy/ftnnml.py
fstd2nc_deps-0.20200304.6.data/purelib/fstd2nc_deps/rpnpy/openanything.py
fstd2nc_deps-0.20200304.6.data/purelib/fstd2nc_deps/rpnpy/rpndate.py
fstd2nc_deps-0.20200304.6.data/purelib/fstd2nc_deps/rpnpy/version.py
fstd2nc_deps-0.20200304.6.data/purelib/fstd2nc_deps/rpnpy/_sharedlibs/__init__.py
fstd2nc_deps-0.20200304.6.data/purelib/fstd2nc_deps/rpnpy/_sharedlibs/libburp_c_shared_1.9.so
fstd2nc_deps-0.20200304.6.data/purelib/fstd2nc_deps/rpnpy/_sharedlibs/libgfortran.so.5
fstd2nc_deps-0.20200304.6.data/purelib/fstd2nc_deps/rpnpy/_sharedlibs/libquadmath.so.0
fstd2nc_deps-0.20200304.6.data/purelib/fstd2nc_deps/rpnpy/_sharedlibs/librmnshared_019.5-rpnpy.so
fstd2nc_deps-0.20200304.6.data/purelib/fstd2nc_deps/rpnpy/_sharedlibs/libvgridshared_6.4.2.so
fstd2nc_deps-0.20200304.6.data/purelib/fstd2nc_deps/rpnpy/burpc/__init__.py
fstd2nc_deps-0.20200304.6.data/purelib/fstd2nc_deps/rpnpy/burpc/all.py
fstd2nc_deps-0.20200304.6.data/purelib/fstd2nc_deps/rpnpy/burpc/base.py
fstd2nc_deps-0.20200304.6.data/purelib/fstd2nc_deps/rpnpy/burpc/brpobj.py
fstd2nc_deps-0.20200304.6.data/purelib/fstd2nc_deps/rpnpy/burpc/const.py
fstd2nc_deps-0.20200304.6.data/purelib/fstd2nc_deps/rpnpy/burpc/proto.py
fstd2nc_deps-0.20200304.6.data/purelib/fstd2nc_deps/rpnpy/librmn/__init__.py
fstd2nc_deps-0.20200304.6.data/purelib/fstd2nc_deps/rpnpy/librmn/all.py
fstd2nc_deps-0.20200304.6.data/purelib/fstd2nc_deps/rpnpy/librmn/base.py
fstd2nc_deps-0.20200304.6.data/purelib/fstd2nc_deps/rpnpy/librmn/burp.py
fstd2nc_deps-0.20200304.6.data/purelib/fstd2nc_deps/rpnpy/librmn/burp_const.py
fstd2nc_deps-0.20200304.6.dist-info/METADATA
fstd2nc_deps-0.20200304.6.dist-info/WHEEL
fstd2nc_deps-0.20200304.6.dist-info/top_level.txt
fstd2nc_deps-0.20200304.6.dist-info/RECORD
