Metadata-Version: 2.1
Name: fstd2nc-deps
Version: 0.20200304.6
Summary: Dependencies for the fstd2nc package.
Home-page: UNKNOWN
Author: Mike Neish
License: LGPL-2.1
Platform: UNKNOWN
Requires-Dist: numpy
Requires-Dist: pytz
